fastapi_provider_aws/__init__.py
fastapi_provider_aws/providers/__init__.py
fastapi_provider_aws/providers/s3.py
fastapi_provider_aws-0.1.0.dist-info/METADATA
fastapi_provider_aws-0.1.0.dist-info/WHEEL
fastapi_provider_aws-0.1.0.dist-info/top_level.txt
fastapi_provider_aws-0.1.0.dist-info/RECORD
