Metadata-Version: 2.4
Name: fastapi-provider-aws
Version: 0.1.0
Summary: AWS S3 provider for FastAPI projects.
Requires-Python: >=3.12
Requires-Dist: fastapi[standard]==0.128
Requires-Dist: boto3>=1.35.0
Requires-Dist: pytest>=9.0.1
Requires-Dist: pytest-asyncio>=0.25.3
Requires-Dist: moto[s3]>=5.0.0
Provides-Extra: dev
